pytest_dfm/__ext__.py
pytest_dfm/__init__.py
pytest_dfm/dv_flow.py
pytest_dfm/impl/ext_rgy.py
pytest_dfm-0.0.117699710753rc0.dist-info/licenses/LICENSE
pytest_dfm-0.0.117699710753rc0.dist-info/METADATA
pytest_dfm-0.0.117699710753rc0.dist-info/WHEEL
pytest_dfm-0.0.117699710753rc0.dist-info/top_level.txt
pytest_dfm-0.0.117699710753rc0.dist-info/RECORD
