Metadata-Version: 2.4
Name: pytest-dfm
Version: 0.0.117699710753rc0
Summary: pytest-dfm provides a pytest integration for DV Flow Manager, a build system for silicon design
Author-email: Matthew Ballance <matt.ballance@gmail.com>
License:                                  Apache License
License-File: LICENSE
Requires-Dist: dv-flow-mgr
Requires-Dist: pytest
Dynamic: license-file
